azure_recommendations_15/__init__.py
azure_recommendations_15/recommendation/__init__.py
azure_recommendations_15/recommendation/advisor_recommendations.py
azure_recommendations_15/recommendation/network_recommendations.py
azure_recommendations_15/recommendation/utils.py
azure_recommendations_15/recommendation/vm_recommendations.py
azure_recommendations_15-0.2.3.dist-info/LICENCE
azure_recommendations_15-0.2.3.dist-info/METADATA
azure_recommendations_15-0.2.3.dist-info/WHEEL
azure_recommendations_15-0.2.3.dist-info/top_level.txt
azure_recommendations_15-0.2.3.dist-info/RECORD
